machinery/__init__.py
machinery/version.py
machinery/dataset/__init__.py
machinery/dataset/downloader.py
machinery/dataset/variables.py
machinery/loader/__init__.py
machinery/loader/ampere.py
machinery/loader/base.py
machinery/loader/laspi.py
machinery/loader/metallicadour.py
machinery_diag-1.0.3.dist-info/LICENSE
machinery_diag-1.0.3.dist-info/METADATA
machinery_diag-1.0.3.dist-info/WHEEL
machinery_diag-1.0.3.dist-info/top_level.txt
machinery_diag-1.0.3.dist-info/RECORD
