Metadata-Version: 2.1
Name: machinery-diag
Version: 1.0.3
Summary: Package for diagnostic open data set
Author: Khaled Benaggoune
Author-email: khaled.mommi@gmail.com
License: MIT
Keywords: phm,diagnostic,machinery
License-File: LICENSE
Requires-Dist: numpy ~=1.26.1
Requires-Dist: pandas ~=2.1.2
Requires-Dist: scikit-learn ~=1.3.2
Requires-Dist: loguru ~=0.7.2
Requires-Dist: setuptools ~=65.5.1
Requires-Dist: tqdm ~=4.66.1
Requires-Dist: openpyxl ~=3.1.2
